girder_job_sequence/__init__.py
girder_job_sequence/job.py
girder_job_sequence/sequence.py
girder_job_sequence/utils.py
girder_job_sequence-0.2.7.dist-info/METADATA
girder_job_sequence-0.2.7.dist-info/WHEEL
girder_job_sequence-0.2.7.dist-info/RECORD
