Metadata-Version: 2.3
Name: girder-job-sequence
Version: 0.2.7
Summary: Utility package for running Girder jobs in a sequence.
Author: Sam Border
Author-email: sam.border2256@gmail.com
Requires-Python: >=3.9
Classifier: Programming Language :: Python :: 3
Classifier: Programming Language :: Python :: 3.9
Classifier: Programming Language :: Python :: 3.10
Classifier: Programming Language :: Python :: 3.11
Classifier: Programming Language :: Python :: 3.12
Classifier: Programming Language :: Python :: 3.13
Requires-Dist: girder-client (>=3.2.8,<4.0.0)
Requires-Dist: lxml (>=5.3.1,<6.0.0)
Requires-Dist: requests (>=2.32.3,<3.0.0)
Requires-Dist: typing-extensions (>=4.12.2,<5.0.0)
Requires-Dist: uuid (>=1.30,<2.0)
